agfusion/__init__.py
agfusion/cli.py
agfusion/database.py
agfusion/exceptions.py
agfusion/model.py
agfusion/parsers.py
agfusion/plot.py
agfusion/utils.py
agfusion/version.py
agfusion-1.4.3.data/scripts/agfusion
agfusion-1.4.3.dist-info/LICENSE.txt
agfusion-1.4.3.dist-info/METADATA
agfusion-1.4.3.dist-info/WHEEL
agfusion-1.4.3.dist-info/top_level.txt
agfusion-1.4.3.dist-info/RECORD
