Metadata-Version: 2.1
Name: agfusion
Version: 1.4.3
Summary: Python package to annotate and visualize gene fusions.
Home-page: https://github.com/murphycj/AGFusion
Author: Charles Murphy
Author-email: murphy.charlesj@gmail.com
License: MIT
License-File: LICENSE.txt
Requires-Dist: matplotlib >=1.5.0
Requires-Dist: pandas >=0.18.1
Requires-Dist: biopython >=1.67
Requires-Dist: future >=0.16.0
Requires-Dist: pyensembl >=1.1.0
